tap_google_play/__init__.py
tap_google_play/__main__.py
tap_google_play/client.py
tap_google_play/streams.py
tap_google_play/tap.py
tap_google_play-0.6.3.dist-info/METADATA
tap_google_play-0.6.3.dist-info/WHEEL
tap_google_play-0.6.3.dist-info/entry_points.txt
tap_google_play-0.6.3.dist-info/licenses/LICENSE
tap_google_play-0.6.3.dist-info/RECORD
