Metadata-Version: 2.4
Name: tap-google-play
Version: 0.6.3
Summary: Singer tap for GooglePlay, built with the Meltano SDK for Singer Taps.
Author-email: hotglue <hello@hotglue.xyz>, Edgar Ramírez-Mondragón <edgarrmondragon@hey.com>
Maintainer-email: Edgar Ramírez-Mondragón <edgarrmondragon@hey.com>
License-Expression: Apache-2.0
License-File: LICENSE
Keywords: ELT,GooglePlay,Meltano,singer.io
Classifier: Programming Language :: Python :: 3 :: Only
Classifier: Programming Language :: Python :: 3.10
Classifier: Programming Language :: Python :: 3.11
Classifier: Programming Language :: Python :: 3.12
Classifier: Programming Language :: Python :: 3.13
Classifier: Programming Language :: Python :: 3.14
Requires-Python: >=3.10
Requires-Dist: google-play-scraper==1.2.7
Requires-Dist: singer-sdk~=0.51.0
